{
  "data": [
    {
      "id": "minor-health-potion",
      "name": "Малое зелье здоровья",
      "description": "Восстанавливает вам 2 ХП",
      "imgPath": "RpgPack/P_Orange02",
      "forWhatGame": 2,
      "canBeBought": true,
      "price": 2
    },
    {
      "id": "minor-mana-potion",
      "name": "Малое зелье маны",
      "description": "Восстанавливает вам 2 маны",
      "imgPath": "RpgPack/P_Blue02",
      "forWhatGame": 2,
      "canBeBought": true,
      "price": 2
    },
    {
      "id": "minor-health-restoration-potion",
      "name": "Малое зелье восстановления здоровья",
      "description": "В течение 4х ходов вы будете восстанавливать по 5 единиц здоровья",
      "imgPath": "RpgPack/P_Orange02",
      "forWhatGame": 2,
      "canBeBought": true,
      "price": 3
    },
    {
      "id": "minor-poison-potion",
      "name": "Слабый яд",
      "description": "В течение 2х ходов враг будет получать по 3 урона",
      "imgPath": "RpgPack/S_Poison02",
      "forWhatGame": 2,
      "canBeBought": true,
      "price": 3
    },
    {
      "id": "fury-blade",
      "name": "Клинок ярости",
      "description": "Пассивный эффект: фишками вы наносите на 2 урона больше",
      "imgPath": "RpgPack/S_Sword16",
      "forWhatGame": 2,
      "canBeBought": true,
      "price": 30
    }
  ]
}